design.v
//  Combinational Circuit
module C_Circuit (a,b,c,o);

//  declaring inputs and output
 input a;
 input b;
 input c;

 output o;

//  Interm Wire

wire X ;

assign x = a | b ;
assign o = x & c ;






endmodule

testbench.v
module tb();

// internal veriable

reg a;
reg b;
reg c;


// wire x; ots not necessory because x is internet variable
wire o;

// Module Design Decleration
 C_Circuit dut(
  
 .a(a),
 .b(b),
 .c(c),
 .o(o)


 );
 // Drive Stimulas
initial begin

 a <= 1'b0;
 b <= 1'b0;
 c <= 1'b0;
 #10;

 a <= 1'b1;
 b <= 1'b1;
 c <= 1'b1;
 #10;

  a <= 1'b0;
 b <= 1'b1;
 c <= 1'b0;
 #10;


 a <= 1'b1;
 b <= 1'b0;
 c <= 1'b1;
 #10;

  a <= 1'b0;
 b <= 1'b0;
 c <= 1'b1;
 #10;

 a <= 1'b1;
 b <= 1'b1;
 c <= 1'b0;
 #10;
  a <= 1'b1;
 b <= 1'b0;
 c <= 1'b0;
 #10;

 a <= 1'b0;
 b <= 1'b1;
 c <= 1'b1;
 #10;


 

  // a <= 1'b1; //1'd1
  // b_1 <= 1'b1;
  // #10;        (1st class Input)

  // a_1 <= 1'b0;
  // b_1 <= 1'b0;
  // #10;
  // a_1 <= 1'b1;
  // b_1 <= 1'b0;
  // #10;
  //  a_1 <= 1'b0;
  // b_1 <= 1'b1;
  // #10;

end

initial begin
  $dumpfile("dump.vcd");
  $dumpvars(0);


end    

endmodule


// iverilog -o out.vpp testbench.v design.v
// vvp out.vpp
// gtkwave dump.vcd

dump.vcd
$date
	Tue Nov 07 12:49:14 2023
$end
$version
	Icarus Verilog
$end
$timescale
	1s
$end
$scope module tb $end
$var wire 1 ! o $end
$var reg 1 " a $end
$var reg 1 # b $end
$var reg 1 $ c $end
$scope module dut $end
$var wire 1 " a $end
$var wire 1 # b $end
$var wire 1 $ c $end
$var wire 1 ! o $end
$var wire 1 % x $end
$upscope $end
$upscope $end
$enddefinitions $end
$comment Show the parameter values. $end
$dumpall
$end
#0
$dumpvars
0%
0$
0#
0"
0!
$end
#10
1!
1%
1$
1#
1"
#20
0!
0$
0"
#30
1!
1$
0#
1"
#40
0!
0%
0"
#50
1%
0$
1#
1"
#60
0#
#70
1!
1$
1#
0"
